pytodo_qt/__init__.py
pytodo_qt/__main__.py
pytodo_qt/core/__init__.py
pytodo_qt/core/config.py
pytodo_qt/core/logger.py
pytodo_qt/core/models.py
pytodo_qt/core/paths.py
pytodo_qt/core/settings.py
pytodo_qt/core/sync_engine.py
pytodo_qt/crypto/__init__.py
pytodo_qt/crypto/aes_gcm.py
pytodo_qt/crypto/kdf.py
pytodo_qt/crypto/key_exchange.py
pytodo_qt/crypto/keyring_storage.py
pytodo_qt/crypto/legacy.py
pytodo_qt/gui/__init__.py
pytodo_qt/gui/main_window.py
pytodo_qt/gui/dialogs/__init__.py
pytodo_qt/gui/dialogs/add_todo.py
pytodo_qt/gui/dialogs/peer_manager.py
pytodo_qt/gui/dialogs/settings.py
pytodo_qt/gui/dialogs/sync.py
pytodo_qt/gui/icons/exit.svg
pytodo_qt/gui/icons/minus.svg
pytodo_qt/gui/icons/plus.svg
pytodo_qt/gui/icons/pytodo-qt.icns
pytodo_qt/gui/icons/pytodo-qt.svg
pytodo_qt/gui/icons/toggle.svg
pytodo_qt/gui/icons/tray.svg
pytodo_qt/gui/styles/__init__.py
pytodo_qt/gui/styles/themes.py
pytodo_qt/gui/widgets/__init__.py
pytodo_qt/gui/widgets/list_selector.py
pytodo_qt/gui/widgets/status_bar.py
pytodo_qt/gui/widgets/todo_table.py
pytodo_qt/net/__init__.py
pytodo_qt/net/client.py
pytodo_qt/net/discovery.py
pytodo_qt/net/protocol.py
pytodo_qt/net/server.py
pytodo_qt-0.3.5.dist-info/licenses/COPYING
pytodo_qt-0.3.5.dist-info/METADATA
pytodo_qt-0.3.5.dist-info/WHEEL
pytodo_qt-0.3.5.dist-info/entry_points.txt
pytodo_qt-0.3.5.dist-info/top_level.txt
pytodo_qt-0.3.5.dist-info/RECORD
