Metadata-Version: 2.4
Name: pytodo-qt
Version: 0.3.5
Summary: A cross-platform to-do list manager with encrypted peer-to-peer synchronization
Author-email: Michael Berry <trismegustis@gmail.com>
License: GPLv3
Project-URL: Homepage, https://github.com/berrym/pytodo-qt
Classifier: Programming Language :: Python :: 3
Classifier: Programming Language :: Python :: 3.11
Classifier: Programming Language :: Python :: 3.12
Classifier: License :: OSI Approved :: GNU General Public License v3 or later (GPLv3+)
Classifier: Operating System :: OS Independent
Requires-Python: >=3.11
License-File: COPYING
Requires-Dist: PyQt6>=6.4
Requires-Dist: cryptography>=41.0
Requires-Dist: zeroconf>=0.80
Requires-Dist: keyring>=24.0
Requires-Dist: qasync>=0.24
Requires-Dist: rich>=13.0
Provides-Extra: dev
Requires-Dist: pytest>=7.0; extra == "dev"
Requires-Dist: pytest-qt>=4.2; extra == "dev"
Requires-Dist: pytest-asyncio>=0.21; extra == "dev"
Requires-Dist: ruff>=0.4; extra == "dev"
Requires-Dist: basedpyright>=1.18; extra == "dev"
Dynamic: license-file
